threedi_scenario_downloader/__init__.py
threedi_scenario_downloader/downloader.py
threedi_scenario_downloader/tests/__init__.py
threedi_scenario_downloader/tests/test_batch.py
threedi_scenario_downloader/tests/test_downloader.py
threedi_scenario_downloader/tests/test_downloader_manual.py
threedi_scenario_downloader/tests/testdata/README.rst
threedi_scenario_downloader/tests/testdata/batch.csv
threedi_scenario_downloader-1.2.dist-info/LICENSE
threedi_scenario_downloader-1.2.dist-info/METADATA
threedi_scenario_downloader-1.2.dist-info/WHEEL
threedi_scenario_downloader-1.2.dist-info/top_level.txt
threedi_scenario_downloader-1.2.dist-info/RECORD
