Metadata-Version: 2.1
Name: threedi-scenario-downloader
Version: 1.2
Summary: Tools for downloading results for 3Di scenarios
Home-page: https://github.com/nens/threedi-scenario-downloader
Author: Emiel Verstegen
Author-email: emiel.verstegen@nelen-schuurmans.nl
License: MIT
Classifier: Programming Language :: Python
Classifier: Framework :: Django
License-File: LICENSE
Requires-Dist: requests
Provides-Extra: test
Requires-Dist: pytest ; extra == 'test'
Requires-Dist: mock ; extra == 'test'
Requires-Dist: pytest-cov ; extra == 'test'
Requires-Dist: pytest-flakes ; extra == 'test'
Requires-Dist: pytest-black ; extra == 'test'
